ragstax/__init__.py
ragstax/chunking/__init__.py
ragstax/chunking/base.py
ragstax/chunking/fixed_token_chunker.py
ragstax/chunking/paragraph_chunker.py
ragstax/chunking/sentence_chunker.py
ragstax-0.1.3.dist-info/METADATA
ragstax-0.1.3.dist-info/WHEEL
ragstax-0.1.3.dist-info/top_level.txt
ragstax-0.1.3.dist-info/RECORD
