Metadata-Version: 2.4
Name: ragstax
Version: 0.1.3
Summary: RAG pipelines
Author-email: Rishabh Deshpande <rishabh9to5@gmail.com>
License: MIT
Requires-Python: >=3.8
Requires-Dist: transformers
Requires-Dist: nltk
